NNSOM/__init__.py
NNSOM/plots.py
NNSOM/som.py
NNSOM/som_gpu.py
NNSOM/utils.py
nnsom-1.8.2.dist-info/METADATA
nnsom-1.8.2.dist-info/WHEEL
nnsom-1.8.2.dist-info/licenses/LICENSE
nnsom-1.8.2.dist-info/RECORD
