Metadata-Version: 2.3
Name: NNSOM
Version: 1.8.2
Summary: A SOM package
Project-URL: Repository, https://github.com/amir-jafari/SOM
Project-URL: Issues, https://github.com/amir-jafari/SOM/issues
Project-URL: Documenation, https://amir-jafari.github.io/SOM/
Author: Dr. Martin Hagan, Dr. Amir Jafari, Lakshmi Sravya Chalapati, Ei Tanaka
License-File: LICENSE
Keywords: Clustering,Machine Learning,Neural Network,SOM,Unsupervised Learning
Requires-Python: >=3.8
